i2c_expanders/PCA9554.py
i2c_expanders/PCA9555.py
i2c_expanders/PCAL9538.py
i2c_expanders/PCAL9554.py
i2c_expanders/PCAL9555.py
i2c_expanders/__init__.py
i2c_expanders/digital_inout.py
i2c_expanders/helpers.py
i2c_expanders/i2c_expander.py
circuitpython_i2c_expanders-1.0.0.dist-info/LICENSE
circuitpython_i2c_expanders-1.0.0.dist-info/METADATA
circuitpython_i2c_expanders-1.0.0.dist-info/WHEEL
circuitpython_i2c_expanders-1.0.0.dist-info/top_level.txt
circuitpython_i2c_expanders-1.0.0.dist-info/RECORD
