Metadata-Version: 2.1
Name: circuitpython-i2c-expanders
Version: 1.0.0
Summary: Drivers for various I2C GPIO expanders.
Author-email: Pat Satyshur <patrick@satyshur.net>
License: MIT
Project-URL: Homepage, https://github.com/ilikecake/CircuitPython_I2C_Expanders
Keywords: adafruit,blinka,circuitpython,micropython,i2c_expanders,pca9555,pcal9555,pca9554,pcal9554,pca9538,pcal9538,i2c,expander,gpio
Classifier: Intended Audience :: Developers
Classifier: Topic :: Software Development :: Libraries
Classifier: Topic :: Software Development :: Embedded Systems
Classifier: Topic :: System :: Hardware
Classifier: License :: OSI Approved :: MIT License
Classifier: Programming Language :: Python :: 3
License-File: LICENSE
Requires-Dist: Adafruit-Blinka
Requires-Dist: adafruit-circuitpython-busdevice
Provides-Extra: optional
